[
  {
    "id": 2574370164,
    "status": "success",
    "stage": "build",
    "name": "bash-shellcheck",
    "ref": "feat/adaptive-pipeline",
    "tag": false,
    "coverage": null,
    "allow_failure": false,
    "created_at": "2022-06-10T12:45:26.885Z",
    "started_at": "2022-06-10T12:45:45.718Z",
    "finished_at": "2022-06-10T12:46:02.260Z",
    "erased_at": null,
    "duration": 16.541508,
    "queued_duration": 0.130826,
    "user": {
      "id": 2835149,
      "username": "pismy",
      "public_email": "",
      "name": "Pierre Smeyers",
      "state": "active",
      "locked": false,
      "avatar_url": "https://gitlab.com/uploads/-/system/user/avatar/2835149/avatar.png",
      "web_url": "https://gitlab.com/pismy",
      "created_at": "2018-09-14T15:22:20.498Z",
      "bio": "",
      "location": "Toulouse, France",
      "linkedin": "pismy",
      "twitter": "@pismy",
      "discord": "",
      "website_url": "",
      "github": "",
      "job_title": "Cloud Solution Architect",
      "pronouns": "",
      "organization": "",
      "bot": false,
      "work_information": "Cloud Solution Architect",
      "followers": 10,
      "following": 2,
      "local_time": "10:53 PM"
    },
    "commit": {
      "id": "7246627cd551115d2f9d317ffda2af2c8b03b0a1",
      "short_id": "7246627c",
      "created_at": "2022-06-10T14:45:19.000+02:00",
      "parent_ids": [
        "0f0c7eb996d186de985608357b9a8448865d0304"
      ],
      "title": "feat: adaptive pipeline",
      "message": "feat: adaptive pipeline\n",
      "author_name": "Pierre Smeyers",
      "author_email": "pierre.smeyers@gmail.com",
      "authored_date": "2022-06-10T14:43:05.000+02:00",
      "committer_name": "Pierre Smeyers",
      "committer_email": "pierre.smeyers@gmail.com",
      "committed_date": "2022-06-10T14:45:19.000+02:00",
      "trailers": {},
      "extended_trailers": {},
      "web_url": "https://gitlab.com/to-be-continuous/node/-/commit/7246627cd551115d2f9d317ffda2af2c8b03b0a1"
    },
    "pipeline": {
      "id": 560769634,
      "iid": 77,
      "project_id": 26454237,
      "sha": "7246627cd551115d2f9d317ffda2af2c8b03b0a1",
      "ref": "feat/adaptive-pipeline",
      "status": "success",
      "source": "push",
      "created_at": "2022-06-10T12:45:26.835Z",
      "updated_at": "2022-06-10T12:46:02.370Z",
      "web_url": "https://gitlab.com/to-be-continuous/node/-/pipelines/560769634"
    },
    "web_url": "https://gitlab.com/to-be-continuous/node/-/jobs/2574370164",
    "project": {
      "ci_job_token_scope_enabled": false
    },
    "artifacts": [
      {
        "file_type": "trace",
        "size": 3314,
        "filename": "job.log",
        "file_format": null
      }
    ],
    "runner": {
      "id": 12270852,
      "description": "3-green.saas-linux-small-amd64.runners-manager.gitlab.com/default",
      "ip_address": null,
      "active": true,
      "paused": false,
      "is_shared": true,
      "runner_type": "instance_type",
      "name": "gitlab-runner",
      "online": false,
      "created_at": "2021-11-15T17:48:54.243Z",
      "status": "stale",
      "job_execution_status": "idle"
    },
    "runner_manager": null,
    "artifacts_expire_at": null,
    "archived": false,
    "tag_list": []
  },
  {
    "id": 2574370162,
    "status": "success",
    "stage": "build",
    "name": "kicker-validation",
    "ref": "feat/adaptive-pipeline",
    "tag": false,
    "coverage": null,
    "allow_failure": false,
    "created_at": "2022-06-10T12:45:26.873Z",
    "started_at": "2022-06-10T12:45:45.667Z",
    "finished_at": "2022-06-10T12:46:01.537Z",
    "erased_at": null,
    "duration": 15.870366,
    "queued_duration": 0.175822,
    "user": {
      "id": 2835149,
      "username": "pismy",
      "public_email": "",
      "name": "Pierre Smeyers",
      "state": "active",
      "locked": false,
      "avatar_url": "https://gitlab.com/uploads/-/system/user/avatar/2835149/avatar.png",
      "web_url": "https://gitlab.com/pismy",
      "created_at": "2018-09-14T15:22:20.498Z",
      "bio": "",
      "location": "Toulouse, France",
      "linkedin": "pismy",
      "twitter": "@pismy",
      "discord": "",
      "website_url": "",
      "github": "",
      "job_title": "Cloud Solution Architect",
      "pronouns": "",
      "organization": "",
      "bot": false,
      "work_information": "Cloud Solution Architect",
      "followers": 10,
      "following": 2,
      "local_time": "10:53 PM"
    },
    "commit": {
      "id": "7246627cd551115d2f9d317ffda2af2c8b03b0a1",
      "short_id": "7246627c",
      "created_at": "2022-06-10T14:45:19.000+02:00",
      "parent_ids": [
        "0f0c7eb996d186de985608357b9a8448865d0304"
      ],
      "title": "feat: adaptive pipeline",
      "message": "feat: adaptive pipeline\n",
      "author_name": "Pierre Smeyers",
      "author_email": "pierre.smeyers@gmail.com",
      "authored_date": "2022-06-10T14:43:05.000+02:00",
      "committer_name": "Pierre Smeyers",
      "committer_email": "pierre.smeyers@gmail.com",
      "committed_date": "2022-06-10T14:45:19.000+02:00",
      "trailers": {},
      "extended_trailers": {},
      "web_url": "https://gitlab.com/to-be-continuous/node/-/commit/7246627cd551115d2f9d317ffda2af2c8b03b0a1"
    },
    "pipeline": {
      "id": 560769634,
      "iid": 77,
      "project_id": 26454237,
      "sha": "7246627cd551115d2f9d317ffda2af2c8b03b0a1",
      "ref": "feat/adaptive-pipeline",
      "status": "success",
      "source": "push",
      "created_at": "2022-06-10T12:45:26.835Z",
      "updated_at": "2022-06-10T12:46:02.370Z",
      "web_url": "https://gitlab.com/to-be-continuous/node/-/pipelines/560769634"
    },
    "web_url": "https://gitlab.com/to-be-continuous/node/-/jobs/2574370162",
    "project": {
      "ci_job_token_scope_enabled": false
    },
    "artifacts": [
      {
        "file_type": "trace",
        "size": 2811,
        "filename": "job.log",
        "file_format": null
      }
    ],
    "runner": {
      "id": 12270845,
      "description": "1-green.saas-linux-small-amd64.runners-manager.gitlab.com/default",
      "ip_address": null,
      "active": true,
      "paused": false,
      "is_shared": true,
      "runner_type": "instance_type",
      "name": "gitlab-runner",
      "online": false,
      "created_at": "2021-11-15T17:48:20.384Z",
      "status": "stale",
      "job_execution_status": "idle"
    },
    "runner_manager": null,
    "artifacts_expire_at": null,
    "archived": false,
    "tag_list": []
  },
  {
    "id": 2574370160,
    "status": "success",
    "stage": "build",
    "name": "gitlab-ci-lint",
    "ref": "feat/adaptive-pipeline",
    "tag": false,
    "coverage": null,
    "allow_failure": false,
    "created_at": "2022-06-10T12:45:26.862Z",
    "started_at": "2022-06-10T12:45:45.497Z",
    "finished_at": "2022-06-10T12:46:01.837Z",
    "erased_at": null,
    "duration": 16.340277,
    "queued_duration": 0.220683,
    "user": {
      "id": 2835149,
      "username": "pismy",
      "public_email": "",
      "name": "Pierre Smeyers",
      "state": "active",
      "locked": false,
      "avatar_url": "https://gitlab.com/uploads/-/system/user/avatar/2835149/avatar.png",
      "web_url": "https://gitlab.com/pismy",
      "created_at": "2018-09-14T15:22:20.498Z",
      "bio": "",
      "location": "Toulouse, France",
      "linkedin": "pismy",
      "twitter": "@pismy",
      "discord": "",
      "website_url": "",
      "github": "",
      "job_title": "Cloud Solution Architect",
      "pronouns": "",
      "organization": "",
      "bot": false,
      "work_information": "Cloud Solution Architect",
      "followers": 10,
      "following": 2,
      "local_time": "10:53 PM"
    },
    "commit": {
      "id": "7246627cd551115d2f9d317ffda2af2c8b03b0a1",
      "short_id": "7246627c",
      "created_at": "2022-06-10T14:45:19.000+02:00",
      "parent_ids": [
        "0f0c7eb996d186de985608357b9a8448865d0304"
      ],
      "title": "feat: adaptive pipeline",
      "message": "feat: adaptive pipeline\n",
      "author_name": "Pierre Smeyers",
      "author_email": "pierre.smeyers@gmail.com",
      "authored_date": "2022-06-10T14:43:05.000+02:00",
      "committer_name": "Pierre Smeyers",
      "committer_email": "pierre.smeyers@gmail.com",
      "committed_date": "2022-06-10T14:45:19.000+02:00",
      "trailers": {},
      "extended_trailers": {},
      "web_url": "https://gitlab.com/to-be-continuous/node/-/commit/7246627cd551115d2f9d317ffda2af2c8b03b0a1"
    },
    "pipeline": {
      "id": 560769634,
      "iid": 77,
      "project_id": 26454237,
      "sha": "7246627cd551115d2f9d317ffda2af2c8b03b0a1",
      "ref": "feat/adaptive-pipeline",
      "status": "success",
      "source": "push",
      "created_at": "2022-06-10T12:45:26.835Z",
      "updated_at": "2022-06-10T12:46:02.370Z",
      "web_url": "https://gitlab.com/to-be-continuous/node/-/pipelines/560769634"
    },
    "web_url": "https://gitlab.com/to-be-continuous/node/-/jobs/2574370160",
    "project": {
      "ci_job_token_scope_enabled": false
    },
    "artifacts": [
      {
        "file_type": "trace",
        "size": 2730,
        "filename": "job.log",
        "file_format": null
      }
    ],
    "runner": {
      "id": 12270852,
      "description": "3-green.saas-linux-small-amd64.runners-manager.gitlab.com/default",
      "ip_address": null,
      "active": true,
      "paused": false,
      "is_shared": true,
      "runner_type": "instance_type",
      "name": "gitlab-runner",
      "online": false,
      "created_at": "2021-11-15T17:48:54.243Z",
      "status": "stale",
      "job_execution_status": "idle"
    },
    "runner_manager": null,
    "artifacts_expire_at": null,
    "archived": false,
    "tag_list": []
  },
  {
    "id": 2574370157,
    "status": "success",
    "stage": ".pre",
    "name": "extract-script",
    "ref": "feat/adaptive-pipeline",
    "tag": false,
    "coverage": null,
    "allow_failure": false,
    "created_at": "2022-06-10T12:45:26.848Z",
    "started_at": "2022-06-10T12:45:27.407Z",
    "finished_at": "2022-06-10T12:45:44.472Z",
    "erased_at": null,
    "duration": 17.065113,
    "queued_duration": 0.254863,
    "user": {
      "id": 2835149,
      "username": "pismy",
      "public_email": "",
      "name": "Pierre Smeyers",
      "state": "active",
      "locked": false,
      "avatar_url": "https://gitlab.com/uploads/-/system/user/avatar/2835149/avatar.png",
      "web_url": "https://gitlab.com/pismy",
      "created_at": "2018-09-14T15:22:20.498Z",
      "bio": "",
      "location": "Toulouse, France",
      "linkedin": "pismy",
      "twitter": "@pismy",
      "discord": "",
      "website_url": "",
      "github": "",
      "job_title": "Cloud Solution Architect",
      "pronouns": "",
      "organization": "",
      "bot": false,
      "work_information": "Cloud Solution Architect",
      "followers": 10,
      "following": 2,
      "local_time": "10:53 PM"
    },
    "commit": {
      "id": "7246627cd551115d2f9d317ffda2af2c8b03b0a1",
      "short_id": "7246627c",
      "created_at": "2022-06-10T14:45:19.000+02:00",
      "parent_ids": [
        "0f0c7eb996d186de985608357b9a8448865d0304"
      ],
      "title": "feat: adaptive pipeline",
      "message": "feat: adaptive pipeline\n",
      "author_name": "Pierre Smeyers",
      "author_email": "pierre.smeyers@gmail.com",
      "authored_date": "2022-06-10T14:43:05.000+02:00",
      "committer_name": "Pierre Smeyers",
      "committer_email": "pierre.smeyers@gmail.com",
      "committed_date": "2022-06-10T14:45:19.000+02:00",
      "trailers": {},
      "extended_trailers": {},
      "web_url": "https://gitlab.com/to-be-continuous/node/-/commit/7246627cd551115d2f9d317ffda2af2c8b03b0a1"
    },
    "pipeline": {
      "id": 560769634,
      "iid": 77,
      "project_id": 26454237,
      "sha": "7246627cd551115d2f9d317ffda2af2c8b03b0a1",
      "ref": "feat/adaptive-pipeline",
      "status": "success",
      "source": "push",
      "created_at": "2022-06-10T12:45:26.835Z",
      "updated_at": "2022-06-10T12:46:02.370Z",
      "web_url": "https://gitlab.com/to-be-continuous/node/-/pipelines/560769634"
    },
    "web_url": "https://gitlab.com/to-be-continuous/node/-/jobs/2574370157",
    "project": {
      "ci_job_token_scope_enabled": false
    },
    "artifacts": [
      {
        "file_type": "trace",
        "size": 2548,
        "filename": "job.log",
        "file_format": null
      }
    ],
    "runner": {
      "id": 12270852,
      "description": "3-green.saas-linux-small-amd64.runners-manager.gitlab.com/default",
      "ip_address": null,
      "active": true,
      "paused": false,
      "is_shared": true,
      "runner_type": "instance_type",
      "name": "gitlab-runner",
      "online": false,
      "created_at": "2021-11-15T17:48:54.243Z",
      "status": "stale",
      "job_execution_status": "idle"
    },
    "runner_manager": null,
    "artifacts_expire_at": "2022-06-10T13:45:41.330Z",
    "archived": false,
    "tag_list": []
  }
]