[
  {
    "id": 9003465333,
    "status": "success",
    "stage": "publish",
    "name": "semantic-release",
    "ref": "master",
    "tag": false,
    "coverage": null,
    "allow_failure": false,
    "created_at": "2025-01-31T02:33:58.239Z",
    "started_at": "2025-01-31T02:34:29.378Z",
    "finished_at": "2025-01-31T02:35:30.863Z",
    "erased_at": null,
    "duration": 61.485225,
    "queued_duration": 0.123887,
    "user": {
      "id": 8838050,
      "username": "tbc-bot",
      "public_email": "",
      "name": "to be continuous bot",
      "state": "active",
      "locked": false,
      "avatar_url": "https://gitlab.com/uploads/-/system/user/avatar/8838050/avatar.png",
      "web_url": "https://gitlab.com/tbc-bot",
      "created_at": "2021-05-06T09:59:49.333Z",
      "bio": "",
      "location": "",
      "linkedin": "",
      "twitter": "",
      "discord": "",
      "website_url": "",
      "github": "",
      "job_title": "",
      "pronouns": null,
      "organization": "",
      "bot": false,
      "work_information": null,
      "followers": 8,
      "following": 0,
      "local_time": "9:47 PM"
    },
    "commit": {
      "id": "13200fa308875d3d0dc4e9e668b070fd4f63ab6e",
      "short_id": "13200fa3",
      "created_at": "2025-01-31T02:33:56.000+00:00",
      "parent_ids": [
        "1850c74063b9194d052720e2e76f21765483ff86",
        "b311c566d9dc0ab6b44ffa704ee3e16ffe678ed1"
      ],
      "title": "Merge branch 'renovate/tbc-deps' into 'master'",
      "message": "Merge branch 'renovate/tbc-deps' into 'master'\n\nchore(deps): update to-be-continuous dependencies\n\nSee merge request to-be-continuous/node!81",
      "author_name": "to be continuous bot",
      "author_email": "pierre.smeyers+tbc@gmail.com",
      "authored_date": "2025-01-31T02:33:56.000+00:00",
      "committer_name": "to be continuous bot",
      "committer_email": "pierre.smeyers+tbc@gmail.com",
      "committed_date": "2025-01-31T02:33:56.000+00:00",
      "trailers": {},
      "extended_trailers": {},
      "web_url": "https://gitlab.com/to-be-continuous/node/-/commit/13200fa308875d3d0dc4e9e668b070fd4f63ab6e"
    },
    "pipeline": {
      "id": 1649515012,
      "iid": 518,
      "project_id": 26454237,
      "sha": "13200fa308875d3d0dc4e9e668b070fd4f63ab6e",
      "ref": "master",
      "status": "success",
      "source": "push",
      "created_at": "2025-01-31T02:33:58.176Z",
      "updated_at": "2025-01-31T02:35:31.120Z",
      "web_url": "https://gitlab.com/to-be-continuous/node/-/pipelines/1649515012"
    },
    "web_url": "https://gitlab.com/to-be-continuous/node/-/jobs/9003465333",
    "project": {
      "ci_job_token_scope_enabled": false
    },
    "artifacts": [
      {
        "file_type": "trace",
        "size": 25736,
        "filename": "job.log",
        "file_format": null
      }
    ],
    "runner": {
      "id": 12270848,
      "description": "2-green.saas-linux-small-amd64.runners-manager.gitlab.com/default",
      "ip_address": null,
      "active": true,
      "paused": false,
      "is_shared": true,
      "runner_type": "instance_type",
      "name": "gitlab-runner",
      "online": false,
      "created_at": "2021-11-15T17:48:38.845Z",
      "status": "stale",
      "job_execution_status": "idle"
    },
    "runner_manager": null,
    "artifacts_expire_at": null,
    "archived": false,
    "tag_list": []
  },
  {
    "id": 9003465332,
    "status": "success",
    "stage": "build",
    "name": "bash-shellcheck",
    "ref": "master",
    "tag": false,
    "coverage": null,
    "allow_failure": false,
    "created_at": "2025-01-31T02:33:58.229Z",
    "started_at": "2025-01-31T02:34:13.728Z",
    "finished_at": "2025-01-31T02:34:25.198Z",
    "erased_at": null,
    "duration": 11.470401,
    "queued_duration": 0.469628,
    "user": {
      "id": 8838050,
      "username": "tbc-bot",
      "public_email": "",
      "name": "to be continuous bot",
      "state": "active",
      "locked": false,
      "avatar_url": "https://gitlab.com/uploads/-/system/user/avatar/8838050/avatar.png",
      "web_url": "https://gitlab.com/tbc-bot",
      "created_at": "2021-05-06T09:59:49.333Z",
      "bio": "",
      "location": "",
      "linkedin": "",
      "twitter": "",
      "discord": "",
      "website_url": "",
      "github": "",
      "job_title": "",
      "pronouns": null,
      "organization": "",
      "bot": false,
      "work_information": null,
      "followers": 8,
      "following": 0,
      "local_time": "9:47 PM"
    },
    "commit": {
      "id": "13200fa308875d3d0dc4e9e668b070fd4f63ab6e",
      "short_id": "13200fa3",
      "created_at": "2025-01-31T02:33:56.000+00:00",
      "parent_ids": [
        "1850c74063b9194d052720e2e76f21765483ff86",
        "b311c566d9dc0ab6b44ffa704ee3e16ffe678ed1"
      ],
      "title": "Merge branch 'renovate/tbc-deps' into 'master'",
      "message": "Merge branch 'renovate/tbc-deps' into 'master'\n\nchore(deps): update to-be-continuous dependencies\n\nSee merge request to-be-continuous/node!81",
      "author_name": "to be continuous bot",
      "author_email": "pierre.smeyers+tbc@gmail.com",
      "authored_date": "2025-01-31T02:33:56.000+00:00",
      "committer_name": "to be continuous bot",
      "committer_email": "pierre.smeyers+tbc@gmail.com",
      "committed_date": "2025-01-31T02:33:56.000+00:00",
      "trailers": {},
      "extended_trailers": {},
      "web_url": "https://gitlab.com/to-be-continuous/node/-/commit/13200fa308875d3d0dc4e9e668b070fd4f63ab6e"
    },
    "pipeline": {
      "id": 1649515012,
      "iid": 518,
      "project_id": 26454237,
      "sha": "13200fa308875d3d0dc4e9e668b070fd4f63ab6e",
      "ref": "master",
      "status": "success",
      "source": "push",
      "created_at": "2025-01-31T02:33:58.176Z",
      "updated_at": "2025-01-31T02:35:31.120Z",
      "web_url": "https://gitlab.com/to-be-continuous/node/-/pipelines/1649515012"
    },
    "web_url": "https://gitlab.com/to-be-continuous/node/-/jobs/9003465332",
    "project": {
      "ci_job_token_scope_enabled": false
    },
    "artifacts": [
      {
        "file_type": "trace",
        "size": 2860,
        "filename": "job.log",
        "file_format": null
      }
    ],
    "runner": {
      "id": 12270859,
      "description": "5-green.saas-linux-small-amd64.runners-manager.gitlab.com/default",
      "ip_address": null,
      "active": true,
      "paused": false,
      "is_shared": true,
      "runner_type": "instance_type",
      "name": "gitlab-runner",
      "online": false,
      "created_at": "2021-11-15T17:49:29.643Z",
      "status": "stale",
      "job_execution_status": "idle"
    },
    "runner_manager": null,
    "artifacts_expire_at": null,
    "archived": false,
    "tag_list": []
  },
  {
    "id": 9003465331,
    "status": "success",
    "stage": "build",
    "name": "kicker-validation",
    "ref": "master",
    "tag": false,
    "coverage": null,
    "allow_failure": false,
    "created_at": "2025-01-31T02:33:58.222Z",
    "started_at": "2025-01-31T02:34:13.681Z",
    "finished_at": "2025-01-31T02:34:26.948Z",
    "erased_at": null,
    "duration": 13.266434,
    "queued_duration": 0.507649,
    "user": {
      "id": 8838050,
      "username": "tbc-bot",
      "public_email": "",
      "name": "to be continuous bot",
      "state": "active",
      "locked": false,
      "avatar_url": "https://gitlab.com/uploads/-/system/user/avatar/8838050/avatar.png",
      "web_url": "https://gitlab.com/tbc-bot",
      "created_at": "2021-05-06T09:59:49.333Z",
      "bio": "",
      "location": "",
      "linkedin": "",
      "twitter": "",
      "discord": "",
      "website_url": "",
      "github": "",
      "job_title": "",
      "pronouns": null,
      "organization": "",
      "bot": false,
      "work_information": null,
      "followers": 8,
      "following": 0,
      "local_time": "9:47 PM"
    },
    "commit": {
      "id": "13200fa308875d3d0dc4e9e668b070fd4f63ab6e",
      "short_id": "13200fa3",
      "created_at": "2025-01-31T02:33:56.000+00:00",
      "parent_ids": [
        "1850c74063b9194d052720e2e76f21765483ff86",
        "b311c566d9dc0ab6b44ffa704ee3e16ffe678ed1"
      ],
      "title": "Merge branch 'renovate/tbc-deps' into 'master'",
      "message": "Merge branch 'renovate/tbc-deps' into 'master'\n\nchore(deps): update to-be-continuous dependencies\n\nSee merge request to-be-continuous/node!81",
      "author_name": "to be continuous bot",
      "author_email": "pierre.smeyers+tbc@gmail.com",
      "authored_date": "2025-01-31T02:33:56.000+00:00",
      "committer_name": "to be continuous bot",
      "committer_email": "pierre.smeyers+tbc@gmail.com",
      "committed_date": "2025-01-31T02:33:56.000+00:00",
      "trailers": {},
      "extended_trailers": {},
      "web_url": "https://gitlab.com/to-be-continuous/node/-/commit/13200fa308875d3d0dc4e9e668b070fd4f63ab6e"
    },
    "pipeline": {
      "id": 1649515012,
      "iid": 518,
      "project_id": 26454237,
      "sha": "13200fa308875d3d0dc4e9e668b070fd4f63ab6e",
      "ref": "master",
      "status": "success",
      "source": "push",
      "created_at": "2025-01-31T02:33:58.176Z",
      "updated_at": "2025-01-31T02:35:31.120Z",
      "web_url": "https://gitlab.com/to-be-continuous/node/-/pipelines/1649515012"
    },
    "web_url": "https://gitlab.com/to-be-continuous/node/-/jobs/9003465331",
    "project": {
      "ci_job_token_scope_enabled": false
    },
    "artifacts": [
      {
        "file_type": "trace",
        "size": 3592,
        "filename": "job.log",
        "file_format": null
      }
    ],
    "runner": {
      "id": 12270845,
      "description": "1-green.saas-linux-small-amd64.runners-manager.gitlab.com/default",
      "ip_address": null,
      "active": true,
      "paused": false,
      "is_shared": true,
      "runner_type": "instance_type",
      "name": "gitlab-runner",
      "online": false,
      "created_at": "2021-11-15T17:48:20.384Z",
      "status": "stale",
      "job_execution_status": "idle"
    },
    "runner_manager": null,
    "artifacts_expire_at": null,
    "archived": false,
    "tag_list": []
  },
  {
    "id": 9003465330,
    "status": "success",
    "stage": "build",
    "name": "tbc-check",
    "ref": "master",
    "tag": false,
    "coverage": null,
    "allow_failure": false,
    "created_at": "2025-01-31T02:33:58.216Z",
    "started_at": "2025-01-31T02:34:13.496Z",
    "finished_at": "2025-01-31T02:34:26.539Z",
    "erased_at": null,
    "duration": 13.043185,
    "queued_duration": 0.413119,
    "user": {
      "id": 8838050,
      "username": "tbc-bot",
      "public_email": "",
      "name": "to be continuous bot",
      "state": "active",
      "locked": false,
      "avatar_url": "https://gitlab.com/uploads/-/system/user/avatar/8838050/avatar.png",
      "web_url": "https://gitlab.com/tbc-bot",
      "created_at": "2021-05-06T09:59:49.333Z",
      "bio": "",
      "location": "",
      "linkedin": "",
      "twitter": "",
      "discord": "",
      "website_url": "",
      "github": "",
      "job_title": "",
      "pronouns": null,
      "organization": "",
      "bot": false,
      "work_information": null,
      "followers": 8,
      "following": 0,
      "local_time": "9:47 PM"
    },
    "commit": {
      "id": "13200fa308875d3d0dc4e9e668b070fd4f63ab6e",
      "short_id": "13200fa3",
      "created_at": "2025-01-31T02:33:56.000+00:00",
      "parent_ids": [
        "1850c74063b9194d052720e2e76f21765483ff86",
        "b311c566d9dc0ab6b44ffa704ee3e16ffe678ed1"
      ],
      "title": "Merge branch 'renovate/tbc-deps' into 'master'",
      "message": "Merge branch 'renovate/tbc-deps' into 'master'\n\nchore(deps): update to-be-continuous dependencies\n\nSee merge request to-be-continuous/node!81",
      "author_name": "to be continuous bot",
      "author_email": "pierre.smeyers+tbc@gmail.com",
      "authored_date": "2025-01-31T02:33:56.000+00:00",
      "committer_name": "to be continuous bot",
      "committer_email": "pierre.smeyers+tbc@gmail.com",
      "committed_date": "2025-01-31T02:33:56.000+00:00",
      "trailers": {},
      "extended_trailers": {},
      "web_url": "https://gitlab.com/to-be-continuous/node/-/commit/13200fa308875d3d0dc4e9e668b070fd4f63ab6e"
    },
    "pipeline": {
      "id": 1649515012,
      "iid": 518,
      "project_id": 26454237,
      "sha": "13200fa308875d3d0dc4e9e668b070fd4f63ab6e",
      "ref": "master",
      "status": "success",
      "source": "push",
      "created_at": "2025-01-31T02:33:58.176Z",
      "updated_at": "2025-01-31T02:35:31.120Z",
      "web_url": "https://gitlab.com/to-be-continuous/node/-/pipelines/1649515012"
    },
    "web_url": "https://gitlab.com/to-be-continuous/node/-/jobs/9003465330",
    "project": {
      "ci_job_token_scope_enabled": false
    },
    "artifacts": [
      {
        "file_type": "trace",
        "size": 6226,
        "filename": "job.log",
        "file_format": null
      }
    ],
    "runner": {
      "id": 12270859,
      "description": "5-green.saas-linux-small-amd64.runners-manager.gitlab.com/default",
      "ip_address": null,
      "active": true,
      "paused": false,
      "is_shared": true,
      "runner_type": "instance_type",
      "name": "gitlab-runner",
      "online": false,
      "created_at": "2021-11-15T17:49:29.643Z",
      "status": "stale",
      "job_execution_status": "idle"
    },
    "runner_manager": null,
    "artifacts_expire_at": null,
    "archived": false,
    "tag_list": []
  },
  {
    "id": 9003465328,
    "status": "success",
    "stage": "build",
    "name": "check-links",
    "ref": "master",
    "tag": false,
    "coverage": null,
    "allow_failure": false,
    "created_at": "2025-01-31T02:33:58.210Z",
    "started_at": "2025-01-31T02:34:13.111Z",
    "finished_at": "2025-01-31T02:34:29.004Z",
    "erased_at": null,
    "duration": 15.892582,
    "queued_duration": 0.163917,
    "user": {
      "id": 8838050,
      "username": "tbc-bot",
      "public_email": "",
      "name": "to be continuous bot",
      "state": "active",
      "locked": false,
      "avatar_url": "https://gitlab.com/uploads/-/system/user/avatar/8838050/avatar.png",
      "web_url": "https://gitlab.com/tbc-bot",
      "created_at": "2021-05-06T09:59:49.333Z",
      "bio": "",
      "location": "",
      "linkedin": "",
      "twitter": "",
      "discord": "",
      "website_url": "",
      "github": "",
      "job_title": "",
      "pronouns": null,
      "organization": "",
      "bot": false,
      "work_information": null,
      "followers": 8,
      "following": 0,
      "local_time": "9:47 PM"
    },
    "commit": {
      "id": "13200fa308875d3d0dc4e9e668b070fd4f63ab6e",
      "short_id": "13200fa3",
      "created_at": "2025-01-31T02:33:56.000+00:00",
      "parent_ids": [
        "1850c74063b9194d052720e2e76f21765483ff86",
        "b311c566d9dc0ab6b44ffa704ee3e16ffe678ed1"
      ],
      "title": "Merge branch 'renovate/tbc-deps' into 'master'",
      "message": "Merge branch 'renovate/tbc-deps' into 'master'\n\nchore(deps): update to-be-continuous dependencies\n\nSee merge request to-be-continuous/node!81",
      "author_name": "to be continuous bot",
      "author_email": "pierre.smeyers+tbc@gmail.com",
      "authored_date": "2025-01-31T02:33:56.000+00:00",
      "committer_name": "to be continuous bot",
      "committer_email": "pierre.smeyers+tbc@gmail.com",
      "committed_date": "2025-01-31T02:33:56.000+00:00",
      "trailers": {},
      "extended_trailers": {},
      "web_url": "https://gitlab.com/to-be-continuous/node/-/commit/13200fa308875d3d0dc4e9e668b070fd4f63ab6e"
    },
    "pipeline": {
      "id": 1649515012,
      "iid": 518,
      "project_id": 26454237,
      "sha": "13200fa308875d3d0dc4e9e668b070fd4f63ab6e",
      "ref": "master",
      "status": "success",
      "source": "push",
      "created_at": "2025-01-31T02:33:58.176Z",
      "updated_at": "2025-01-31T02:35:31.120Z",
      "web_url": "https://gitlab.com/to-be-continuous/node/-/pipelines/1649515012"
    },
    "web_url": "https://gitlab.com/to-be-continuous/node/-/jobs/9003465328",
    "project": {
      "ci_job_token_scope_enabled": false
    },
    "artifacts": [
      {
        "file_type": "trace",
        "size": 2646,
        "filename": "job.log",
        "file_format": null
      }
    ],
    "runner": {
      "id": 32976645,
      "description": "6-green.saas-linux-small-amd64.runners-manager.gitlab.com/default",
      "ip_address": null,
      "active": true,
      "paused": false,
      "is_shared": true,
      "runner_type": "instance_type",
      "name": null,
      "online": false,
      "created_by": {
        "id": 6515150,
        "username": "rhassanein-admin",
        "public_email": "",
        "name": "Rehab Hassanein",
        "state": "active",
        "locked": false,
        "avatar_url": "https://secure.gravatar.com/avatar/f666d7b03304319b77d3e0eef49a7ea0f3f97f813536109786338b6468d7d34f?s=80&d=identicon",
        "web_url": "https://gitlab.com/rhassanein-admin"
      },
      "created_at": "2024-02-21T14:49:55.159Z",
      "status": "stale",
      "job_execution_status": "idle"
    },
    "runner_manager": null,
    "artifacts_expire_at": null,
    "archived": false,
    "tag_list": []
  },
  {
    "id": 9003465327,
    "status": "success",
    "stage": "build",
    "name": "gitlab-ci-lint",
    "ref": "master",
    "tag": false,
    "coverage": null,
    "allow_failure": false,
    "created_at": "2025-01-31T02:33:58.201Z",
    "started_at": "2025-01-31T02:34:12.894Z",
    "finished_at": "2025-01-31T02:34:25.269Z",
    "erased_at": null,
    "duration": 12.374588,
    "queued_duration": 0.147133,
    "user": {
      "id": 8838050,
      "username": "tbc-bot",
      "public_email": "",
      "name": "to be continuous bot",
      "state": "active",
      "locked": false,
      "avatar_url": "https://gitlab.com/uploads/-/system/user/avatar/8838050/avatar.png",
      "web_url": "https://gitlab.com/tbc-bot",
      "created_at": "2021-05-06T09:59:49.333Z",
      "bio": "",
      "location": "",
      "linkedin": "",
      "twitter": "",
      "discord": "",
      "website_url": "",
      "github": "",
      "job_title": "",
      "pronouns": null,
      "organization": "",
      "bot": false,
      "work_information": null,
      "followers": 8,
      "following": 0,
      "local_time": "9:47 PM"
    },
    "commit": {
      "id": "13200fa308875d3d0dc4e9e668b070fd4f63ab6e",
      "short_id": "13200fa3",
      "created_at": "2025-01-31T02:33:56.000+00:00",
      "parent_ids": [
        "1850c74063b9194d052720e2e76f21765483ff86",
        "b311c566d9dc0ab6b44ffa704ee3e16ffe678ed1"
      ],
      "title": "Merge branch 'renovate/tbc-deps' into 'master'",
      "message": "Merge branch 'renovate/tbc-deps' into 'master'\n\nchore(deps): update to-be-continuous dependencies\n\nSee merge request to-be-continuous/node!81",
      "author_name": "to be continuous bot",
      "author_email": "pierre.smeyers+tbc@gmail.com",
      "authored_date": "2025-01-31T02:33:56.000+00:00",
      "committer_name": "to be continuous bot",
      "committer_email": "pierre.smeyers+tbc@gmail.com",
      "committed_date": "2025-01-31T02:33:56.000+00:00",
      "trailers": {},
      "extended_trailers": {},
      "web_url": "https://gitlab.com/to-be-continuous/node/-/commit/13200fa308875d3d0dc4e9e668b070fd4f63ab6e"
    },
    "pipeline": {
      "id": 1649515012,
      "iid": 518,
      "project_id": 26454237,
      "sha": "13200fa308875d3d0dc4e9e668b070fd4f63ab6e",
      "ref": "master",
      "status": "success",
      "source": "push",
      "created_at": "2025-01-31T02:33:58.176Z",
      "updated_at": "2025-01-31T02:35:31.120Z",
      "web_url": "https://gitlab.com/to-be-continuous/node/-/pipelines/1649515012"
    },
    "web_url": "https://gitlab.com/to-be-continuous/node/-/jobs/9003465327",
    "project": {
      "ci_job_token_scope_enabled": false
    },
    "artifacts": [
      {
        "file_type": "trace",
        "size": 2797,
        "filename": "job.log",
        "file_format": null
      }
    ],
    "runner": {
      "id": 12270852,
      "description": "3-green.saas-linux-small-amd64.runners-manager.gitlab.com/default",
      "ip_address": null,
      "active": true,
      "paused": false,
      "is_shared": true,
      "runner_type": "instance_type",
      "name": "gitlab-runner",
      "online": false,
      "created_at": "2021-11-15T17:48:54.243Z",
      "status": "stale",
      "job_execution_status": "idle"
    },
    "runner_manager": null,
    "artifacts_expire_at": null,
    "archived": false,
    "tag_list": []
  },
  {
    "id": 9003465325,
    "status": "success",
    "stage": ".pre",
    "name": "extract-script",
    "ref": "master",
    "tag": false,
    "coverage": null,
    "allow_failure": false,
    "created_at": "2025-01-31T02:33:58.190Z",
    "started_at": "2025-01-31T02:33:59.137Z",
    "finished_at": "2025-01-31T02:34:12.547Z",
    "erased_at": null,
    "duration": 13.409573,
    "queued_duration": 0.097498,
    "user": {
      "id": 8838050,
      "username": "tbc-bot",
      "public_email": "",
      "name": "to be continuous bot",
      "state": "active",
      "locked": false,
      "avatar_url": "https://gitlab.com/uploads/-/system/user/avatar/8838050/avatar.png",
      "web_url": "https://gitlab.com/tbc-bot",
      "created_at": "2021-05-06T09:59:49.333Z",
      "bio": "",
      "location": "",
      "linkedin": "",
      "twitter": "",
      "discord": "",
      "website_url": "",
      "github": "",
      "job_title": "",
      "pronouns": null,
      "organization": "",
      "bot": false,
      "work_information": null,
      "followers": 8,
      "following": 0,
      "local_time": "9:47 PM"
    },
    "commit": {
      "id": "13200fa308875d3d0dc4e9e668b070fd4f63ab6e",
      "short_id": "13200fa3",
      "created_at": "2025-01-31T02:33:56.000+00:00",
      "parent_ids": [
        "1850c74063b9194d052720e2e76f21765483ff86",
        "b311c566d9dc0ab6b44ffa704ee3e16ffe678ed1"
      ],
      "title": "Merge branch 'renovate/tbc-deps' into 'master'",
      "message": "Merge branch 'renovate/tbc-deps' into 'master'\n\nchore(deps): update to-be-continuous dependencies\n\nSee merge request to-be-continuous/node!81",
      "author_name": "to be continuous bot",
      "author_email": "pierre.smeyers+tbc@gmail.com",
      "authored_date": "2025-01-31T02:33:56.000+00:00",
      "committer_name": "to be continuous bot",
      "committer_email": "pierre.smeyers+tbc@gmail.com",
      "committed_date": "2025-01-31T02:33:56.000+00:00",
      "trailers": {},
      "extended_trailers": {},
      "web_url": "https://gitlab.com/to-be-continuous/node/-/commit/13200fa308875d3d0dc4e9e668b070fd4f63ab6e"
    },
    "pipeline": {
      "id": 1649515012,
      "iid": 518,
      "project_id": 26454237,
      "sha": "13200fa308875d3d0dc4e9e668b070fd4f63ab6e",
      "ref": "master",
      "status": "success",
      "source": "push",
      "created_at": "2025-01-31T02:33:58.176Z",
      "updated_at": "2025-01-31T02:35:31.120Z",
      "web_url": "https://gitlab.com/to-be-continuous/node/-/pipelines/1649515012"
    },
    "web_url": "https://gitlab.com/to-be-continuous/node/-/jobs/9003465325",
    "project": {
      "ci_job_token_scope_enabled": false
    },
    "artifacts": [
      {
        "file_type": "trace",
        "size": 3112,
        "filename": "job.log",
        "file_format": null
      }
    ],
    "runner": {
      "id": 32976645,
      "description": "6-green.saas-linux-small-amd64.runners-manager.gitlab.com/default",
      "ip_address": null,
      "active": true,
      "paused": false,
      "is_shared": true,
      "runner_type": "instance_type",
      "name": null,
      "online": false,
      "created_by": {
        "id": 6515150,
        "username": "rhassanein-admin",
        "public_email": "",
        "name": "Rehab Hassanein",
        "state": "active",
        "locked": false,
        "avatar_url": "https://secure.gravatar.com/avatar/f666d7b03304319b77d3e0eef49a7ea0f3f97f813536109786338b6468d7d34f?s=80&d=identicon",
        "web_url": "https://gitlab.com/rhassanein-admin"
      },
      "created_at": "2024-02-21T14:49:55.159Z",
      "status": "stale",
      "job_execution_status": "idle"
    },
    "runner_manager": null,
    "artifacts_expire_at": "2025-01-31T03:34:09.769Z",
    "archived": false,
    "tag_list": []
  }
]